{
    "last_updated": "2026-03-03 05:02:21 UTC",
    "total_articles": 6,
    "bullish_articles": 2,
    "bearish_articles": 4,
    "articles": [
        {
            "title": "Markets begin to react as Trump\u2019s attack on Iran risks hitting American pocketbooks - The Washington Post",
            "sentiment": "NEGATIVE",
            "score": 0.8735648989677429,
            "signal": "BEARISH",
            "tickers": [],
            "primary_ticker": null,
            "ticker_impacts": []
        },
        {
            "title": "Prediction market trader 'Magamyman' made $553,000 on death of Iran's supreme leader - NPR",
            "sentiment": "NEGATIVE",
            "score": 0.8579465746879578,
            "signal": "BEARISH",
            "tickers": [],
            "primary_ticker": null,
            "ticker_impacts": []
        },
        {
            "title": "Oil prices fallout: OPEC producers boost output after Iran strikes - Axios",
            "sentiment": "POSITIVE",
            "score": 0.9395676255226135,
            "signal": "BULLISH",
            "tickers": [],
            "primary_ticker": null,
            "ticker_impacts": []
        },
        {
            "title": "When AI Meets Geopolitics - TipRanks",
            "sentiment": "NEGATIVE",
            "score": 0.9050730466842651,
            "signal": "BEARISH",
            "tickers": [],
            "primary_ticker": null,
            "ticker_impacts": []
        },
        {
            "title": "Jack Dorsey\u2019s 4,000 Job Cuts at Block Arouse Suspicions of AI-Washing - Bloomberg.com",
            "sentiment": "NEGATIVE",
            "score": 0.939295768737793,
            "signal": "BEARISH",
            "tickers": [
                "INTC"
            ],
            "primary_ticker": null,
            "ticker_impacts": [
                {
                    "ticker": "INTC",
                    "impact": "negative",
                    "relevance": "medium"
                }
            ]
        },
        {
            "title": "NVIDIA and Global Telecom Leaders Commit to Build 6G on Open and Secure AI-Native Platforms - NVIDIA Newsroom",
            "sentiment": "POSITIVE",
            "score": 0.7793379426002502,
            "signal": "BULLISH",
            "tickers": [
                "NVDA"
            ],
            "primary_ticker": "NVDA",
            "ticker_impacts": [
                {
                    "ticker": "NVDA",
                    "impact": "positive",
                    "relevance": "high"
                }
            ]
        }
    ]
}