[
    {
        "title": "AI-generated ads dropped the ball at this year\u2019s Super Bowl - theverge.com",
        "sentiment": "NEGATIVE",
        "score": 0.7685912251472473,
        "signal": "BEARISH",
        "tickers": [],
        "primary_ticker": null,
        "ticker_impacts": []
    },
    {
        "title": "S&P 500 rises, led by tech; Dow climbs to fresh record: Live updates - CNBC",
        "sentiment": "POSITIVE",
        "score": 0.8564398884773254,
        "signal": "BULLISH",
        "tickers": [],
        "primary_ticker": null,
        "ticker_impacts": []
    },
    {
        "title": "FDA says Novo Nordisk's TV ad for obesity pill includes 'false or misleading' claims - CNBC",
        "sentiment": "NEGATIVE",
        "score": 0.8504900336265564,
        "signal": "BEARISH",
        "tickers": [],
        "primary_ticker": null,
        "ticker_impacts": []
    },
    {
        "title": "Monday Stock: Monday.com Earnings Beat. Software Maker's Guidance Disappoints. - Investor's Business Daily",
        "sentiment": "NEGATIVE",
        "score": 0.9685027599334717,
        "signal": "BEARISH",
        "tickers": [],
        "primary_ticker": null,
        "ticker_impacts": []
    },
    {
        "title": "Eddie Bauer's retail operator declares bankruptcy - cbsnews.com",
        "sentiment": "NEGATIVE",
        "score": 0.9675112366676331,
        "signal": "BEARISH",
        "tickers": [],
        "primary_ticker": null,
        "ticker_impacts": []
    },
    {
        "title": "Kyndryl Shares Halved Amid CFO Departure, Accounting Review - The Wall Street Journal",
        "sentiment": "NEGATIVE",
        "score": 0.9752050042152405,
        "signal": "BEARISH",
        "tickers": [],
        "primary_ticker": null,
        "ticker_impacts": []
    },
    {
        "title": "AI Stocks Turn Choppy. Hyperscaler Capex Explodes. Software Hammered. - Investor's Business Daily",
        "sentiment": "NEGATIVE",
        "score": 0.8951002359390259,
        "signal": "BEARISH",
        "tickers": [],
        "primary_ticker": null,
        "ticker_impacts": []
    },
    {
        "title": "Blue Owl Founders Pledged $1.9 Billion Stake Before Stock Plunge - Bloomberg.com",
        "sentiment": "NEGATIVE",
        "score": 0.9347513318061829,
        "signal": "BEARISH",
        "tickers": [],
        "primary_ticker": null,
        "ticker_impacts": []
    },
    {
        "title": "US dollar slammed lower even as data shows the shorts piling in - investingLive",
        "sentiment": "NEGATIVE",
        "score": 0.962465226650238,
        "signal": "BEARISH",
        "tickers": [],
        "primary_ticker": null,
        "ticker_impacts": []
    },
    {
        "title": "Oracle Stock Upgraded By Analyst To A Buy Call Amid Deep Slump. Here's Why. - Investor's Business Daily",
        "sentiment": "POSITIVE",
        "score": 0.9469723701477051,
        "signal": "BULLISH",
        "tickers": [],
        "primary_ticker": null,
        "ticker_impacts": []
    },
    {
        "title": "Novo Nordisk Says It\u2019s Suing Hims to Halt Obesity Drug Copycats - Bloomberg.com",
        "sentiment": "NEGATIVE",
        "score": 0.9363986253738403,
        "signal": "BEARISH",
        "tickers": [],
        "primary_ticker": null,
        "ticker_impacts": []
    },
    {
        "title": "US Homeowners Staying Put for Longest Since 2000 - Newser",
        "sentiment": "NEGATIVE",
        "score": 0.8154568672180176,
        "signal": "BEARISH",
        "tickers": [],
        "primary_ticker": null,
        "ticker_impacts": []
    },
    {
        "title": "China might be beginning to back away from U.S. debt as investors get nervous about overexposure to American assets - Fortune",
        "sentiment": "NEGATIVE",
        "score": 0.9562086462974548,
        "signal": "BEARISH",
        "tickers": [],
        "primary_ticker": null,
        "ticker_impacts": []
    },
    {
        "title": "Crypto revolt exposes fragility of Trump's coalition - Axios",
        "sentiment": "NEGATIVE",
        "score": 0.8990916609764099,
        "signal": "BEARISH",
        "tickers": [],
        "primary_ticker": null,
        "ticker_impacts": []
    },
    {
        "title": "Meta warned EU plans to impose measures on tech giant to reverse WhatsApp AI policy - CNBC",
        "sentiment": "NEGATIVE",
        "score": 0.8651552796363831,
        "signal": "BEARISH",
        "tickers": [
            "META"
        ],
        "primary_ticker": "META",
        "ticker_impacts": [
            {
                "ticker": "META",
                "impact": "negative",
                "relevance": "high"
            }
        ]
    },
    {
        "title": "Beijing\u2019s Growth Model Is Still Broken - Foreign Affairs",
        "sentiment": "NEGATIVE",
        "score": 0.9614397287368774,
        "signal": "BEARISH",
        "tickers": [],
        "primary_ticker": null,
        "ticker_impacts": []
    },
    {
        "title": "Dow futures rise after index tops 50,000 for first time while landslide election in Japan sends U.S. bond yields higher - Fortune",
        "sentiment": "POSITIVE",
        "score": 0.8865311741828918,
        "signal": "BULLISH",
        "tickers": [],
        "primary_ticker": null,
        "ticker_impacts": []
    },
    {
        "title": "J.P. Morgan Says \u2018Ignore the Noise\u2019 on Alphabet Stock - TipRanks",
        "sentiment": "NEGATIVE",
        "score": 0.9172545075416565,
        "signal": "BEARISH",
        "tickers": [
            "GOOGL"
        ],
        "primary_ticker": "GOOGL",
        "ticker_impacts": [
            {
                "ticker": "GOOGL",
                "impact": "negative",
                "relevance": "high"
            }
        ]
    },
    {
        "title": "Apprenticeship clearing system to be introduced - BBC",
        "sentiment": "NEGATIVE",
        "score": 0.743668258190155,
        "signal": "BEARISH",
        "tickers": [],
        "primary_ticker": null,
        "ticker_impacts": []
    },
    {
        "title": "Goldman Sachs $80 Billion Warning: BTC, Gold & Silver Exposed? - BeInCrypto",
        "sentiment": "NEGATIVE",
        "score": 0.9309049844741821,
        "signal": "BEARISH",
        "tickers": [
            "GS"
        ],
        "primary_ticker": "GS",
        "ticker_impacts": [
            {
                "ticker": "GS",
                "impact": "negative",
                "relevance": "high"
            }
        ]
    },
    {
        "title": "Washington Post Staff Starts GoFundMe For International Employees Facing \u201cSerious Security Risks\u201d After Layoffs: \u201cI Was Just Laid Off In The Middle Of A War Zone\u201d - Deadline",
        "sentiment": "NEGATIVE",
        "score": 0.9405501484870911,
        "signal": "BEARISH",
        "tickers": [],
        "primary_ticker": null,
        "ticker_impacts": []
    },
    {
        "title": "Japan\u2019s Katayama Ready to Talk with Market on Monday If Needed - bloomberg.com",
        "sentiment": "POSITIVE",
        "score": 0.7123581171035767,
        "signal": "BULLISH",
        "tickers": [],
        "primary_ticker": null,
        "ticker_impacts": []
    },
    {
        "title": "Gambling Stocks Sag as Prediction Markets Steal Super Bowl Bets - Bloomberg.com",
        "sentiment": "NEGATIVE",
        "score": 0.9125828742980957,
        "signal": "BEARISH",
        "tickers": [],
        "primary_ticker": null,
        "ticker_impacts": []
    },
    {
        "title": "Economists reject Kevin Warsh\u2019s claim that AI boom will enable rate cuts - Financial Times",
        "sentiment": "NEGATIVE",
        "score": 0.8902682662010193,
        "signal": "BEARISH",
        "tickers": [],
        "primary_ticker": null,
        "ticker_impacts": []
    },
    {
        "title": "Markets will soon test a Musk merger that promises 'space-based internet' - NBC News",
        "sentiment": "POSITIVE",
        "score": 0.8549548387527466,
        "signal": "BULLISH",
        "tickers": [],
        "primary_ticker": null,
        "ticker_impacts": []
    }
]