[
    {
        "title": "Tesla dodges 30-day suspension in California after removing Autopilot - TechCrunch",
        "sentiment": "NEGATIVE",
        "score": 0.9199557304382324,
        "signal": "BEARISH",
        "tickers": [
            "TSLA"
        ],
        "primary_ticker": "TSLA",
        "ticker_impacts": [
            {
                "ticker": "TSLA",
                "impact": "negative",
                "relevance": "high"
            }
        ]
    },
    {
        "title": "There\u2019s a New Term for Workers Freaking Out Over Being Replaced by AI - Gizmodo",
        "sentiment": "NEGATIVE",
        "score": 0.8812935948371887,
        "signal": "BEARISH",
        "tickers": [],
        "primary_ticker": null,
        "ticker_impacts": []
    },
    {
        "title": "US stocks edge higher after swinging through worries about AI and the economy - AP News",
        "sentiment": "POSITIVE",
        "score": 0.9087709188461304,
        "signal": "BULLISH",
        "tickers": [],
        "primary_ticker": null,
        "ticker_impacts": []
    },
    {
        "title": "Ted Sarandos Slams Paramount for \u2018Flooding the Zone With Misinformation\u2019 as Warner Bros. Discovery Initiates New Talks With Rival Suitor - Variety",
        "sentiment": "NEGATIVE",
        "score": 0.9145727753639221,
        "signal": "BEARISH",
        "tickers": [
            "NFLX"
        ],
        "primary_ticker": null,
        "ticker_impacts": [
            {
                "ticker": "NFLX",
                "impact": "negative",
                "relevance": "medium"
            }
        ]
    },
    {
        "title": "What the 10-year Treasury\u2019s move toward 4% says about AI anxiety in markets - MarketWatch",
        "sentiment": "NEGATIVE",
        "score": 0.9020140767097473,
        "signal": "BEARISH",
        "tickers": [],
        "primary_ticker": null,
        "ticker_impacts": []
    },
    {
        "title": "Sandisk drops after Western Digital confirms plan to unload $3 billion in stock - Sherwood News",
        "sentiment": "NEGATIVE",
        "score": 0.8067914247512817,
        "signal": "BEARISH",
        "tickers": [],
        "primary_ticker": null,
        "ticker_impacts": []
    },
    {
        "title": "Trump crackdown drives 80% plunge in immigrant employment, reshaping labor market, Goldman says - Fortune",
        "sentiment": "NEGATIVE",
        "score": 0.9269459843635559,
        "signal": "BEARISH",
        "tickers": [],
        "primary_ticker": null,
        "ticker_impacts": []
    },
    {
        "title": "PANW Earnings: Palo Alto Networks Stock Sinks Despite Top and Bottom Line Beats - TipRanks",
        "sentiment": "NEGATIVE",
        "score": 0.9631071090698242,
        "signal": "BEARISH",
        "tickers": [],
        "primary_ticker": null,
        "ticker_impacts": []
    },
    {
        "title": "Nvidia secures multibillion-dollar Meta deal as it battles chip rivals - Financial Times",
        "sentiment": "POSITIVE",
        "score": 0.8300252556800842,
        "signal": "BULLISH",
        "tickers": [
            "NVDA",
            "META"
        ],
        "primary_ticker": "NVDA",
        "ticker_impacts": [
            {
                "ticker": "NVDA",
                "impact": "positive",
                "relevance": "high"
            },
            {
                "ticker": "META",
                "impact": "positive",
                "relevance": "high"
            }
        ]
    },
    {
        "title": "Oil Falls After Iran Calls Nuclear Talks With US Constructive - Bloomberg",
        "sentiment": "NEGATIVE",
        "score": 0.9397765398025513,
        "signal": "BEARISH",
        "tickers": [],
        "primary_ticker": null,
        "ticker_impacts": []
    },
    {
        "title": "Amazon pulls the plug on 'Blue Jay' warehouse robot after only a few months - Business Insider",
        "sentiment": "NEGATIVE",
        "score": 0.923004150390625,
        "signal": "BEARISH",
        "tickers": [
            "AMZN"
        ],
        "primary_ticker": "AMZN",
        "ticker_impacts": [
            {
                "ticker": "AMZN",
                "impact": "negative",
                "relevance": "high"
            }
        ]
    },
    {
        "title": "Humanoid robots show off creepily impressive kung-fu moves during Lunar New Year festival in China - Live Science",
        "sentiment": "POSITIVE",
        "score": 0.8882051110267639,
        "signal": "BULLISH",
        "tickers": [],
        "primary_ticker": null,
        "ticker_impacts": []
    },
    {
        "title": "National Fast Food Chain To Close Hundreds Of Restaurants; New Hampshire Locations May Be Impacted - Patch",
        "sentiment": "NEGATIVE",
        "score": 0.9638992547988892,
        "signal": "BEARISH",
        "tickers": [],
        "primary_ticker": null,
        "ticker_impacts": []
    },
    {
        "title": "Ford\u2019s $30,000 EV pickup beats every other truck in one key area - Electrek",
        "sentiment": "POSITIVE",
        "score": 0.8123070597648621,
        "signal": "BULLISH",
        "tickers": [],
        "primary_ticker": null,
        "ticker_impacts": []
    },
    {
        "title": "$56 trillion national debt leading to a spiraling crisis: budget watchdog warns the U.S. is walking a crumbling path - Fortune",
        "sentiment": "NEGATIVE",
        "score": 0.9373726844787598,
        "signal": "BEARISH",
        "tickers": [],
        "primary_ticker": null,
        "ticker_impacts": []
    },
    {
        "title": "Wall Street Is Sizing Up Warsh\u2019s Options to Shrink Fed Portfolio - Bloomberg",
        "sentiment": "NEGATIVE",
        "score": 0.9385330080986023,
        "signal": "BEARISH",
        "tickers": [],
        "primary_ticker": null,
        "ticker_impacts": []
    },
    {
        "title": "Shein\u2019s \u2018addictive design\u2019 and illegal sex dolls under investigation - The Verge",
        "sentiment": "NEGATIVE",
        "score": 0.8263598680496216,
        "signal": "BEARISH",
        "tickers": [],
        "primary_ticker": null,
        "ticker_impacts": []
    },
    {
        "title": "EU privacy investigation targets Musk\u2019s Grok chatbot over sexualized deepfake images - AP News",
        "sentiment": "NEGATIVE",
        "score": 0.7681806683540344,
        "signal": "BEARISH",
        "tickers": [],
        "primary_ticker": null,
        "ticker_impacts": []
    },
    {
        "title": "Adani pledges $100B to build AI data centers as India seeks bigger role in the global AI race - TechCrunch",
        "sentiment": "POSITIVE",
        "score": 0.7303019165992737,
        "signal": "BULLISH",
        "tickers": [
            "GOOGL",
            "MSFT"
        ],
        "primary_ticker": null,
        "ticker_impacts": [
            {
                "ticker": "GOOGL",
                "impact": "positive",
                "relevance": "medium"
            },
            {
                "ticker": "MSFT",
                "impact": "positive",
                "relevance": "medium"
            }
        ]
    },
    {
        "title": "Thomas Pritzker steps down as Hyatt executive chair over Epstein ties - Financial Times",
        "sentiment": "NEGATIVE",
        "score": 0.8328593969345093,
        "signal": "BEARISH",
        "tickers": [],
        "primary_ticker": null,
        "ticker_impacts": []
    },
    {
        "title": "Postal union president focused on keeping USPS an \u2018affordable option,\u2019 amid agency\u2019s financial woes - Federal News Network",
        "sentiment": "POSITIVE",
        "score": 0.7400542497634888,
        "signal": "BULLISH",
        "tickers": [],
        "primary_ticker": null,
        "ticker_impacts": []
    },
    {
        "title": "Bitcoin on Pace for Longest Losing Streak Since 2018 Bear Market - Decrypt",
        "sentiment": "NEGATIVE",
        "score": 0.9567352533340454,
        "signal": "BEARISH",
        "tickers": [],
        "primary_ticker": null,
        "ticker_impacts": []
    },
    {
        "title": "Ford is asking the Trump Administration to allow Chinese EV tech in the US - Electrek",
        "sentiment": "POSITIVE",
        "score": 0.7013727426528931,
        "signal": "BULLISH",
        "tickers": [],
        "primary_ticker": null,
        "ticker_impacts": []
    }
]