{
    "last_updated": "2026-03-21 18:58:31 UTC",
    "total_articles": 26,
    "bullish_articles": 6,
    "bearish_articles": 20,
    "articles": [
        {
            "title": "Stocks slip, head for fourth-straight losing week as Iran war continues: Live updates - CNBC",
            "sentiment": "NEGATIVE",
            "score": 0.9730141758918762,
            "signal": "BEARISH",
            "tickers": [],
            "primary_ticker": null,
            "ticker_impacts": []
        },
        {
            "title": "Traders Lift Bets on a Fed Hike This Year to 50% as Yields Surge - Bloomberg.com",
            "sentiment": "NEGATIVE",
            "score": 0.801372230052948,
            "signal": "BEARISH",
            "tickers": [],
            "primary_ticker": null,
            "ticker_impacts": []
        },
        {
            "title": "UK government borrowing costs hit their highest level since 2008 as inflation fears hit the gilt market - CNBC",
            "sentiment": "NEGATIVE",
            "score": 0.8536520004272461,
            "signal": "BEARISH",
            "tickers": [],
            "primary_ticker": null,
            "ticker_impacts": []
        },
        {
            "title": "Super Micro shares plunge as US charges co-founder, 2 more for smuggling AI chips to China - Yahoo Finance",
            "sentiment": "NEGATIVE",
            "score": 0.9724482297897339,
            "signal": "BEARISH",
            "tickers": [],
            "primary_ticker": null,
            "ticker_impacts": []
        },
        {
            "title": "Global oil price stuck in triple digits. Goldman Sachs says it may stay there for years - CNN",
            "sentiment": "NEGATIVE",
            "score": 0.9669309854507446,
            "signal": "BEARISH",
            "tickers": [
                "GS"
            ],
            "primary_ticker": "GS",
            "ticker_impacts": [
                {
                    "ticker": "GS",
                    "impact": "negative",
                    "relevance": "high"
                }
            ]
        },
        {
            "title": "Alibaba, Tencent Shed $66 Billion After AI Vision Falls Flat - Bloomberg.com",
            "sentiment": "NEGATIVE",
            "score": 0.9729028940200806,
            "signal": "BEARISH",
            "tickers": [
                "INTC"
            ],
            "primary_ticker": null,
            "ticker_impacts": [
                {
                    "ticker": "INTC",
                    "impact": "negative",
                    "relevance": "medium"
                }
            ]
        },
        {
            "title": "Novartis agrees to acquire a pan-mutant-selective PI3K\u03b1 inhibitor, strengthening its breast cancer pipeline - Novartis",
            "sentiment": "POSITIVE",
            "score": 0.9478443264961243,
            "signal": "BULLISH",
            "tickers": [],
            "primary_ticker": null,
            "ticker_impacts": []
        },
        {
            "title": "Jensen Huang says he will be 'deeply alarmed' if his $500,000 engineer did not consume at least $250,000 of tokens - Business Insider",
            "sentiment": "NEGATIVE",
            "score": 0.711449921131134,
            "signal": "BEARISH",
            "tickers": [
                "NVDA"
            ],
            "primary_ticker": null,
            "ticker_impacts": [
                {
                    "ticker": "NVDA",
                    "impact": "negative",
                    "relevance": "medium"
                }
            ]
        },
        {
            "title": "Exclusive | Saudi Arabia Sees a Spike to $180 Oil if Energy Shock Persists Past April - WSJ",
            "sentiment": "POSITIVE",
            "score": 0.8276510238647461,
            "signal": "BULLISH",
            "tickers": [],
            "primary_ticker": null,
            "ticker_impacts": []
        },
        {
            "title": "Gold prices rebound but head for deep weekly loss as Iran war dents rate cut bets - Investing.com",
            "sentiment": "NEGATIVE",
            "score": 0.9415228366851807,
            "signal": "BEARISH",
            "tickers": [],
            "primary_ticker": null,
            "ticker_impacts": []
        },
        {
            "title": "Asian Stocks to Steady as US Shares Pare Drop: Markets Wrap - Bloomberg.com",
            "sentiment": "NEGATIVE",
            "score": 0.8769725561141968,
            "signal": "BEARISH",
            "tickers": [],
            "primary_ticker": null,
            "ticker_impacts": []
        },
        {
            "title": "ARM Stock Forecast Jumps 46% as Citi Analyst Notes that Arm\u2019s Newest Tech Commands \u201c2x the Royalty Rate\u201d - TipRanks",
            "sentiment": "POSITIVE",
            "score": 0.9437531232833862,
            "signal": "BULLISH",
            "tickers": [
                "ARM",
                "C",
                "INTC"
            ],
            "primary_ticker": null,
            "ticker_impacts": [
                {
                    "ticker": "ARM",
                    "impact": "positive",
                    "relevance": "medium"
                },
                {
                    "ticker": "C",
                    "impact": "positive",
                    "relevance": "medium"
                },
                {
                    "ticker": "INTC",
                    "impact": "positive",
                    "relevance": "medium"
                }
            ]
        },
        {
            "title": "FDA Approves New High-Dose Wegovy in US For Boosted Weight Loss - ScienceAlert",
            "sentiment": "POSITIVE",
            "score": 0.8855046033859253,
            "signal": "BULLISH",
            "tickers": [
                "AP"
            ],
            "primary_ticker": null,
            "ticker_impacts": [
                {
                    "ticker": "AP",
                    "impact": "positive",
                    "relevance": "medium"
                }
            ]
        },
        {
            "title": "The Worst-Case Economic Outcome of Trump\u2019s Iran War - The Bulwark",
            "sentiment": "NEGATIVE",
            "score": 0.8862429857254028,
            "signal": "BEARISH",
            "tickers": [],
            "primary_ticker": null,
            "ticker_impacts": []
        },
        {
            "title": "Jet fuel prices jumped 60 percent: Your next flight will cost more - thestreet.com",
            "sentiment": "NEGATIVE",
            "score": 0.9251730442047119,
            "signal": "BEARISH",
            "tickers": [],
            "primary_ticker": null,
            "ticker_impacts": []
        },
        {
            "title": "Iran Leaves an Isolated Trump Grappling With Historic Oil Crisis - Bloomberg.com",
            "sentiment": "NEGATIVE",
            "score": 0.9416793584823608,
            "signal": "BEARISH",
            "tickers": [],
            "primary_ticker": null,
            "ticker_impacts": []
        },
        {
            "title": "Justice Department probe of Powell could backfire on Trump and keep Fed chair in office - PBS",
            "sentiment": "NEGATIVE",
            "score": 0.8159432411193848,
            "signal": "BEARISH",
            "tickers": [],
            "primary_ticker": null,
            "ticker_impacts": []
        },
        {
            "title": "Micron Stock Falls As Investors Suspect Peak Is Near And Take Profits - Investor's Business Daily",
            "sentiment": "NEGATIVE",
            "score": 0.9423037767410278,
            "signal": "BEARISH",
            "tickers": [],
            "primary_ticker": null,
            "ticker_impacts": []
        },
        {
            "title": "Eli Lilly Confirms 'Superior Weight Loss' Of Its Next-Generation Obesity Drug - Investor's Business Daily",
            "sentiment": "NEGATIVE",
            "score": 0.9440554976463318,
            "signal": "BEARISH",
            "tickers": [],
            "primary_ticker": null,
            "ticker_impacts": []
        },
        {
            "title": "Average U.S. long-term mortgage rate rises to 6.22%, highest in more than 3 months - PBS",
            "sentiment": "NEGATIVE",
            "score": 0.9269014000892639,
            "signal": "BEARISH",
            "tickers": [],
            "primary_ticker": null,
            "ticker_impacts": []
        },
        {
            "title": "Houston's richest neighborhood hit with insane gas prices - Chron",
            "sentiment": "NEGATIVE",
            "score": 0.923191249370575,
            "signal": "BEARISH",
            "tickers": [],
            "primary_ticker": null,
            "ticker_impacts": []
        },
        {
            "title": "FBI seizes website tied to Iranian cyberattack on U.S. company, hacker group says - NBC News",
            "sentiment": "NEGATIVE",
            "score": 0.9040265679359436,
            "signal": "BEARISH",
            "tickers": [],
            "primary_ticker": null,
            "ticker_impacts": []
        },
        {
            "title": "'A Critical Breaking Point': TSA Issues Emergency Warning To O'Hare And Midway Amid Unprecedented Staffing Crisis - Secret Chicago",
            "sentiment": "POSITIVE",
            "score": 0.8034127950668335,
            "signal": "BULLISH",
            "tickers": [],
            "primary_ticker": null,
            "ticker_impacts": []
        },
        {
            "title": "Rivian sacrifices 2027 profit goal to push deeper into autonomy - TechCrunch",
            "sentiment": "NEGATIVE",
            "score": 0.9065510630607605,
            "signal": "BEARISH",
            "tickers": [],
            "primary_ticker": null,
            "ticker_impacts": []
        },
        {
            "title": "Fortune 500 firm updates AI price tag to $4.5 trillion, estimating 93% of jobs vulnerable to disruption - Fortune",
            "sentiment": "POSITIVE",
            "score": 0.7925513386726379,
            "signal": "BULLISH",
            "tickers": [],
            "primary_ticker": null,
            "ticker_impacts": []
        },
        {
            "title": "USPS warning raises stakes for mail-order prescriptions, higher postage prices - Axios",
            "sentiment": "NEGATIVE",
            "score": 0.9349998235702515,
            "signal": "BEARISH",
            "tickers": [
                "AMZN"
            ],
            "primary_ticker": null,
            "ticker_impacts": [
                {
                    "ticker": "AMZN",
                    "impact": "negative",
                    "relevance": "medium"
                }
            ]
        }
    ]
}