{
    "last_updated": "2026-03-13 03:12:40 UTC",
    "total_articles": 17,
    "bullish_articles": 4,
    "bearish_articles": 13,
    "articles": [
        {
            "title": "Morgan Stanley Limits Redemptions on Private Credit Fund - Bloomberg",
            "sentiment": "NEGATIVE",
            "score": 0.844015896320343,
            "signal": "BEARISH",
            "tickers": [],
            "primary_ticker": null,
            "ticker_impacts": []
        },
        {
            "title": "Dow Falls to Lowest Close This Year After Oil\u2019s Latest Climb - WSJ",
            "sentiment": "NEGATIVE",
            "score": 0.9026623368263245,
            "signal": "BEARISH",
            "tickers": [],
            "primary_ticker": null,
            "ticker_impacts": []
        },
        {
            "title": "SEPTA's Market-Frankford Line service resumes after transformer fire in Philadelphia - 6abc Philadelphia",
            "sentiment": "NEGATIVE",
            "score": 0.952526330947876,
            "signal": "BEARISH",
            "tickers": [],
            "primary_ticker": null,
            "ticker_impacts": []
        },
        {
            "title": "Trump's war on Iran creates an economic storm for consumers and the Fed - NBC News",
            "sentiment": "NEGATIVE",
            "score": 0.9169974327087402,
            "signal": "BEARISH",
            "tickers": [],
            "primary_ticker": null,
            "ticker_impacts": []
        },
        {
            "title": "CFTC and SEC Announce Historic Memorandum of Understanding Between Agencies - Commodity Futures Trading Commission | CFTC (.gov)",
            "sentiment": "POSITIVE",
            "score": 0.9243423342704773,
            "signal": "BULLISH",
            "tickers": [
                "MOU"
            ],
            "primary_ticker": null,
            "ticker_impacts": [
                {
                    "ticker": "MOU",
                    "impact": "positive",
                    "relevance": "medium"
                }
            ]
        },
        {
            "title": "The Live Nation settlement has industry insiders baffled - The Verge",
            "sentiment": "NEGATIVE",
            "score": 0.924480676651001,
            "signal": "BEARISH",
            "tickers": [],
            "primary_ticker": null,
            "ticker_impacts": []
        },
        {
            "title": "Airline Raised Flight Price From $4,000 to $28,000, as War Hits Travel Budgets - Fodors Travel Guide",
            "sentiment": "POSITIVE",
            "score": 0.9190981388092041,
            "signal": "BULLISH",
            "tickers": [],
            "primary_ticker": null,
            "ticker_impacts": []
        },
        {
            "title": "After a year of pressure, activists call off Target boycott - Axios",
            "sentiment": "NEGATIVE",
            "score": 0.9246394038200378,
            "signal": "BEARISH",
            "tickers": [],
            "primary_ticker": null,
            "ticker_impacts": []
        },
        {
            "title": "Private credit crisis is a result of 'really bad underwriting' - PIMCO - Seeking Alpha",
            "sentiment": "NEGATIVE",
            "score": 0.8952122926712036,
            "signal": "BEARISH",
            "tickers": [],
            "primary_ticker": null,
            "ticker_impacts": []
        },
        {
            "title": "Nvidia Invests $2 Billion In Nebius To Fund AI Data Center Buildout - Investor's Business Daily",
            "sentiment": "POSITIVE",
            "score": 0.8641812205314636,
            "signal": "BULLISH",
            "tickers": [
                "NVDA"
            ],
            "primary_ticker": "NVDA",
            "ticker_impacts": [
                {
                    "ticker": "NVDA",
                    "impact": "positive",
                    "relevance": "high"
                }
            ]
        },
        {
            "title": "More pain in private credit with JPMorgan reportedly tightening lending while a $33 billion fund sees heavy redemptions - MarketWatch",
            "sentiment": "NEGATIVE",
            "score": 0.9560132622718811,
            "signal": "BEARISH",
            "tickers": [
                "JPM"
            ],
            "primary_ticker": "JPM",
            "ticker_impacts": [
                {
                    "ticker": "JPM",
                    "impact": "negative",
                    "relevance": "high"
                }
            ]
        },
        {
            "title": "Oracle's Larry Ellison Downplays Software Apocalypse Fears - Business Insider",
            "sentiment": "NEGATIVE",
            "score": 0.8452342748641968,
            "signal": "BEARISH",
            "tickers": [],
            "primary_ticker": null,
            "ticker_impacts": []
        },
        {
            "title": "DISH Loses 226 ABC, CBS, FOX, & NBC Stations - | Cord Cutters News",
            "sentiment": "NEGATIVE",
            "score": 0.967029333114624,
            "signal": "BEARISH",
            "tickers": [],
            "primary_ticker": null,
            "ticker_impacts": []
        },
        {
            "title": "Assemblyman Gray calls North Star\u2019s plan to put Wintergreen at helm 'absurd;' Hochul says discussions for receivership are underway - North Country Now",
            "sentiment": "NEGATIVE",
            "score": 0.944818913936615,
            "signal": "BEARISH",
            "tickers": [],
            "primary_ticker": null,
            "ticker_impacts": []
        },
        {
            "title": "Amazon\u2019s Massive Bond Sale Draws $126 Billion in Orders, One of the Largest Ever - TipRanks",
            "sentiment": "POSITIVE",
            "score": 0.9008793830871582,
            "signal": "BULLISH",
            "tickers": [
                "AMZN"
            ],
            "primary_ticker": "AMZN",
            "ticker_impacts": [
                {
                    "ticker": "AMZN",
                    "impact": "positive",
                    "relevance": "high"
                }
            ]
        },
        {
            "title": "Judge orders Perplexity to stop AI agents from shopping on Amazon - The Verge",
            "sentiment": "NEGATIVE",
            "score": 0.8887466788291931,
            "signal": "BEARISH",
            "tickers": [
                "AMZN"
            ],
            "primary_ticker": "AMZN",
            "ticker_impacts": [
                {
                    "ticker": "AMZN",
                    "impact": "negative",
                    "relevance": "high"
                }
            ]
        },
        {
            "title": "FDA Warns Novo Nordisk of Unreported Side Effects Tied to GLP-1 Patients - WSJ",
            "sentiment": "NEGATIVE",
            "score": 0.8819292783737183,
            "signal": "BEARISH",
            "tickers": [],
            "primary_ticker": null,
            "ticker_impacts": []
        }
    ]
}