[
    {
        "title": "Washington Post chief executive steps down after mass lay-offs - BBC",
        "sentiment": "NEGATIVE",
        "score": 0.9456327557563782,
        "signal": "BEARISH",
        "tickers": [],
        "primary_ticker": null,
        "ticker_impacts": []
    },
    {
        "title": "Gambling Stocks Sag as Prediction Markets Steal Super Bowl Bets - Bloomberg.com",
        "sentiment": "NEGATIVE",
        "score": 0.9125828742980957,
        "signal": "BEARISH",
        "tickers": [],
        "primary_ticker": null,
        "ticker_impacts": []
    },
    {
        "title": "Chipotle launches free offer for customers amid struggles - thestreet.com",
        "sentiment": "POSITIVE",
        "score": 0.8970429301261902,
        "signal": "BULLISH",
        "tickers": [],
        "primary_ticker": null,
        "ticker_impacts": []
    },
    {
        "title": "Trump wants to run the economy hot, as midterm elections approach - The Washington Post",
        "sentiment": "POSITIVE",
        "score": 0.8703634142875671,
        "signal": "BULLISH",
        "tickers": [],
        "primary_ticker": null,
        "ticker_impacts": []
    },
    {
        "title": "Silver Price Forecast: Why the Pullback From $120 Could Fuel the Next Rally - FXEmpire",
        "sentiment": "POSITIVE",
        "score": 0.8049345016479492,
        "signal": "BULLISH",
        "tickers": [],
        "primary_ticker": null,
        "ticker_impacts": []
    },
    {
        "title": "\"Trump slump\" threatens to doom World Cup bump - Salon.com",
        "sentiment": "NEGATIVE",
        "score": 0.8986812233924866,
        "signal": "BEARISH",
        "tickers": [],
        "primary_ticker": null,
        "ticker_impacts": []
    },
    {
        "title": "Economists reject Kevin Warsh\u2019s claim that AI boom will enable rate cuts - Financial Times",
        "sentiment": "NEGATIVE",
        "score": 0.8902682662010193,
        "signal": "BEARISH",
        "tickers": [],
        "primary_ticker": null,
        "ticker_impacts": []
    },
    {
        "title": "Markets will soon test a Musk merger that promises 'space-based internet' - NBC News",
        "sentiment": "POSITIVE",
        "score": 0.8549548387527466,
        "signal": "BULLISH",
        "tickers": [],
        "primary_ticker": null,
        "ticker_impacts": []
    },
    {
        "title": "6 New Buys As Many Sectors Thrive, But Market Still Split - Investor's Business Daily",
        "sentiment": "NEGATIVE",
        "score": 0.7460373640060425,
        "signal": "BEARISH",
        "tickers": [],
        "primary_ticker": null,
        "ticker_impacts": []
    },
    {
        "title": "Troubled gunmaker files Chapter 11 bankruptcy after ATF dispute - thestreet.com",
        "sentiment": "NEGATIVE",
        "score": 0.9100472331047058,
        "signal": "BEARISH",
        "tickers": [],
        "primary_ticker": null,
        "ticker_impacts": []
    },
    {
        "title": "Crypto Company Accidentally Gives $44 Billion to Customers - The Daily Beast",
        "sentiment": "NEGATIVE",
        "score": 0.7955501675605774,
        "signal": "BEARISH",
        "tickers": [],
        "primary_ticker": null,
        "ticker_impacts": []
    },
    {
        "title": "Hims & Hers drops plan for knockoff of Novo Nordisk\u2019s new Wegovy weight loss pill - AP News",
        "sentiment": "NEGATIVE",
        "score": 0.9578995704650879,
        "signal": "BEARISH",
        "tickers": [],
        "primary_ticker": null,
        "ticker_impacts": []
    },
    {
        "title": "Dorsey\u2019s Block Cutting Up to 10% of Staff in Efficiency Push - Bloomberg.com",
        "sentiment": "NEGATIVE",
        "score": 0.9692033529281616,
        "signal": "BEARISH",
        "tickers": [],
        "primary_ticker": null,
        "ticker_impacts": []
    },
    {
        "title": "The U.S. construction industry's need for labor is soaring and will need half a million new workers next year while AI giants ramp up spending - Fortune",
        "sentiment": "POSITIVE",
        "score": 0.9362689256668091,
        "signal": "BULLISH",
        "tickers": [],
        "primary_ticker": null,
        "ticker_impacts": []
    },
    {
        "title": "Nearly a thousand Google workers sign letter urging company to divest from ICE, CBP - CNBC",
        "sentiment": "NEGATIVE",
        "score": 0.9470521211624146,
        "signal": "BEARISH",
        "tickers": [
            "GOOGL"
        ],
        "primary_ticker": "GOOGL",
        "ticker_impacts": [
            {
                "ticker": "GOOGL",
                "impact": "negative",
                "relevance": "high"
            }
        ]
    },
    {
        "title": "Creditors accuse Optimum of \u2018weaponising\u2019 antitrust laws to avoid bankruptcy - Financial Times",
        "sentiment": "NEGATIVE",
        "score": 0.935520589351654,
        "signal": "BEARISH",
        "tickers": [],
        "primary_ticker": null,
        "ticker_impacts": []
    },
    {
        "title": "Mail delivery delays in Durham neighborhood: residents await answers amid USPS winter weather impact - ABC11 Raleigh-Durham",
        "sentiment": "NEGATIVE",
        "score": 0.9291121363639832,
        "signal": "BEARISH",
        "tickers": [],
        "primary_ticker": null,
        "ticker_impacts": []
    },
    {
        "title": "Wall Street\u2019s wild week rattles investors\u2019 confidence while highlighting a growing divide within markets - MarketWatch",
        "sentiment": "NEGATIVE",
        "score": 0.7617092728614807,
        "signal": "BEARISH",
        "tickers": [],
        "primary_ticker": null,
        "ticker_impacts": []
    },
    {
        "title": "American Pilots Write To Board, Demand \"Decisive Change\" From Management - One Mile at a Time",
        "sentiment": "NEGATIVE",
        "score": 0.8710395097732544,
        "signal": "BEARISH",
        "tickers": [],
        "primary_ticker": null,
        "ticker_impacts": []
    },
    {
        "title": "Stellantis Stumbles In A Staggering EV Retreat - CleanTechnica",
        "sentiment": "NEGATIVE",
        "score": 0.9610152840614319,
        "signal": "BEARISH",
        "tickers": [],
        "primary_ticker": null,
        "ticker_impacts": []
    },
    {
        "title": "Automakers largely sit out 2026 Super Bowl advertising amid industry uncertainty - CNBC",
        "sentiment": "NEGATIVE",
        "score": 0.8851498961448669,
        "signal": "BEARISH",
        "tickers": [],
        "primary_ticker": null,
        "ticker_impacts": []
    },
    {
        "title": "BART\u2019s cost-cutting plan risks a \u2018death spiral\u2019 that could end all train service - San Francisco Chronicle",
        "sentiment": "NEGATIVE",
        "score": 0.82063889503479,
        "signal": "BEARISH",
        "tickers": [],
        "primary_ticker": null,
        "ticker_impacts": []
    },
    {
        "title": "Tech stocks have been shaky, but these 20 companies could still see rocketing sales growth - MarketWatch",
        "sentiment": "POSITIVE",
        "score": 0.7435473203659058,
        "signal": "BULLISH",
        "tickers": [],
        "primary_ticker": null,
        "ticker_impacts": []
    },
    {
        "title": "Once popular restaurant stuns patrons by announcing closure of all locations - PennLive",
        "sentiment": "NEGATIVE",
        "score": 0.8132089376449585,
        "signal": "BEARISH",
        "tickers": [],
        "primary_ticker": null,
        "ticker_impacts": []
    },
    {
        "title": "Payments platform BridgePay confirms ransomware attack behind outage - BleepingComputer",
        "sentiment": "NEGATIVE",
        "score": 0.9416335225105286,
        "signal": "BEARISH",
        "tickers": [],
        "primary_ticker": null,
        "ticker_impacts": []
    },
    {
        "title": "One question is haunting laid-off Big Tech workers: Did AI just cost me my job? - Business Insider",
        "sentiment": "NEGATIVE",
        "score": 0.7393822073936462,
        "signal": "BEARISH",
        "tickers": [],
        "primary_ticker": null,
        "ticker_impacts": []
    },
    {
        "title": "NASA seeks to bolster workforce, reduce reliance on contractors - SpaceNews",
        "sentiment": "NEGATIVE",
        "score": 0.8754264712333679,
        "signal": "BEARISH",
        "tickers": [],
        "primary_ticker": null,
        "ticker_impacts": []
    },
    {
        "title": "Google Calls on Governments And Industry to Prepare Now For Quantum-Era Cybersecurity - The Quantum Insider",
        "sentiment": "POSITIVE",
        "score": 0.7343884110450745,
        "signal": "BULLISH",
        "tickers": [
            "GOOGL"
        ],
        "primary_ticker": "GOOGL",
        "ticker_impacts": [
            {
                "ticker": "GOOGL",
                "impact": "positive",
                "relevance": "high"
            }
        ]
    }
]